imagesplitter/__init__.py
imagesplitter/__main__.py
imagesplitter/paper.py
imagesplitter/printerpaper.py
imagesplitter/splitter.py
imagesplitter-1.0.2.dist-info/LICENSE
imagesplitter-1.0.2.dist-info/METADATA
imagesplitter-1.0.2.dist-info/WHEEL
imagesplitter-1.0.2.dist-info/entry_points.txt
imagesplitter-1.0.2.dist-info/top_level.txt
imagesplitter-1.0.2.dist-info/RECORD
