Metadata-Version: 2.1
Name: imagesplitter
Version: 1.0.2
Summary: CLI tool for turning images into printable PDFs.
Home-page: https://github.com/wciesialka/image-splitter
Author: Willow Ciesialka
Author-email: wciesialka@gmail.com
License: MIT
Keywords: python image ascii art
Platform: UNKNOWN
Classifier: License :: OSI Approved :: MIT License
Classifier: Programming Language :: Python :: 3
Classifier: Topic :: Artistic Software
Classifier: Operating System :: OS Independent
Requires-Python: >=3.8.10
Requires-Dist: Pillow (==8.4.0)
